[
  {
    "id": "main",
    "components": [
      "section",
      "tab"
    ]
  },
  {
    "id": "section",
    "components": [
      "text",
      "image",
      "button",
      "title",
      "hero",
      "hero-quote",
      "hero-subscription",
      "cards",
      "cards-category",
      "cards-product",
      "cards-steps",
      "columns",
      "fragment",
      "accordion-faq",
      "banner",
      "embed"
    ]
  },
  {
    "id": "accordion-faq",
    "components": [
      "accordion-faq-item"
    ]
  },
  {
    "id": "cards-category",
    "components": [
      "cards-category-card"
    ]
  },
  {
    "id": "cards-product",
    "components": [
      "cards-product-card"
    ]
  },
  {
    "id": "cards-steps",
    "components": [
      "cards-steps-card"
    ]
  },
  {
    "id": "cards",
    "components": [
      "cards-card"
    ]
  },
  {
    "id": "columns",
    "components": [
      "column"
    ]
  },
  {
    "id": "column",
    "components": [
      "text",
      "image",
      "button",
      "title"
    ]
  }
]